mcp_rag_librarian-0.3.1.dist-info/licenses/LICENSE
rag_mcp_server/server.py
rag_mcp_server/core/application_state.py
rag_mcp_server/core/config_manager.py
rag_mcp_server/core/document_processor.py
rag_mcp_server/core/document_store.py
rag_mcp_server/core/embedding_service.py
rag_mcp_server/core/faiss_index.py
rag_mcp_server/core/file_persistence.py
rag_mcp_server/core/knowledge_base_manager.py
rag_mcp_server/core/persistence.py
rag_mcp_server/core/persistence_factory.py
rag_mcp_server/core/response_models.py
rag_mcp_server/core/service_container.py
rag_mcp_server/core/tool_registry.py
rag_mcp_server/interfaces/knowledge_base_interfaces.py
mcp_rag_librarian-0.3.1.dist-info/METADATA
mcp_rag_librarian-0.3.1.dist-info/WHEEL
mcp_rag_librarian-0.3.1.dist-info/entry_points.txt
mcp_rag_librarian-0.3.1.dist-info/top_level.txt
mcp_rag_librarian-0.3.1.dist-info/RECORD
