Metadata-Version: 2.4
Name: mcp-rag-librarian
Version: 0.3.1
Summary: MCP server for RAG (Retrieval-Augmented Generation) operations with local document indexing - Fork with enhancements
Author-email: Tommaso Maria Ungetti <tommaso.ungetti@outlook.com>, "Yang Liu (delexw)" <adamyoungliu@gmail.com>
Maintainer-email: "Yang Liu (delexw)" <adamyoungliu@gmail.com>
License: MIT
Project-URL: Homepage, https://github.com/delexw/mcp-rag-librarian
Project-URL: Repository, https://github.com/delexw/mcp-rag-librarian
Project-URL: Documentation, https://github.com/delexw/mcp-rag-librarian#readme
Project-URL: Bug Tracker, https://github.com/delexw/mcp-rag-librarian/issues
Project-URL: Original Repository, https://github.com/tungetti/rag-mcp-server
Keywords: mcp,rag,retrieval,embedding,semantic-search,ai,llm
Classifier: Development Status :: 4 - Beta
Classifier: Intended Audience :: Developers
Classifier: License :: OSI Approved :: MIT License
Classifier: Operating System :: OS Independent
Classifier: Programming Language :: Python :: 3
Classifier: Programming Language :: Python :: 3.9
Classifier: Programming Language :: Python :: 3.10
Classifier: Programming Language :: Python :: 3.11
Classifier: Programming Language :: Python :: 3.12
Classifier: Programming Language :: Python :: 3.13
Classifier: Topic :: Scientific/Engineering :: Artificial Intelligence
Classifier: Topic :: Software Development :: Libraries :: Python Modules
Classifier: Topic :: Text Processing :: Indexing
Requires-Python: >=3.9
License-File: LICENSE
Requires-Dist: faiss-cpu>=1.7.0
Requires-Dist: mcp>=1.9.0
Requires-Dist: numpy>=1.21.0
Requires-Dist: pydantic>=2.0.0
Requires-Dist: pymupdf>=1.23.0
Requires-Dist: sentence-transformers>=2.0.0
Requires-Dist: tqdm>=4.64.0
Provides-Extra: dev
Requires-Dist: pytest>=7.0.0; extra == "dev"
Requires-Dist: black>=22.0.0; extra == "dev"
Requires-Dist: isort>=5.0.0; extra == "dev"
Requires-Dist: mypy>=1.0.0; extra == "dev"
Dynamic: license-file
